gazeMapper/__init__.py
gazeMapper/config.py
gazeMapper/episode.py
gazeMapper/marker.py
gazeMapper/naming.py
gazeMapper/plane.py
gazeMapper/project_watcher.py
gazeMapper/session.py
gazeMapper/synchronization.py
gazeMapper/type_utils.py
gazeMapper/typed_dict_defaults.py
gazeMapper/version.py
gazeMapper/GUI/__init__.py
gazeMapper/GUI/_impl/__init__.py
gazeMapper/GUI/_impl/callbacks.py
gazeMapper/GUI/_impl/gui.py
gazeMapper/GUI/_impl/image_helper.py
gazeMapper/GUI/_impl/session_lister.py
gazeMapper/GUI/_impl/settings_editor.py
gazeMapper/GUI/_impl/utils.py
gazeMapper/process/__init__.py
gazeMapper/process/_utils.py
gazeMapper/process/auto_code_episodes.py
gazeMapper/process/auto_code_sync_points.py
gazeMapper/process/code_episodes.py
gazeMapper/process/detect_markers.py
gazeMapper/process/export_trials.py
gazeMapper/process/gaze_to_plane.py
gazeMapper/process/make_gaze_overlay_video.py
gazeMapper/process/make_mapped_gaze_video.py
gazeMapper/process/run_validation.py
gazeMapper/process/sync_et_to_cam.py
gazeMapper/process/sync_to_ref.py
gazeMapper/utils/__init__.py
gazeMapper/utils/color_blob_localizer.py
gazemapper-1.8.4.dist-info/licenses/LICENSE
gazemapper-1.8.4.dist-info/METADATA
gazemapper-1.8.4.dist-info/WHEEL
gazemapper-1.8.4.dist-info/entry_points.txt
gazemapper-1.8.4.dist-info/top_level.txt
gazemapper-1.8.4.dist-info/RECORD
