Metadata-Version: 2.4
Name: gazeMapper
Version: 1.8.4
Summary: Automated world-based analysis of wearable eye tracker data.
Home-page: https://github.com/dcnieho/gazeMapper
Author: Diederick Niehorster
Author-email: diederick_c.niehorster@humlab.lu.se
License: MIT License
Project-URL: Source Code, https://github.com/dcnieho/gazeMapper
Classifier: Programming Language :: Python :: 3.11
Classifier: License :: OSI Approved :: MIT License
Classifier: Operating System :: OS Independent
Requires-Python: >=3.11
License-File: LICENSE
Requires-Dist: glassesTools[GUI]~=1.23.0
Requires-Dist: typeguard
Requires-Dist: uvloop; sys_platform != "win32"
Requires-Dist: pyobjc-framework-Cocoa; sys_platform == "darwin"
Requires-Dist: watchfiles
Dynamic: author
Dynamic: author-email
Dynamic: classifier
Dynamic: description
Dynamic: description-content-type
Dynamic: home-page
Dynamic: license
Dynamic: license-file
Dynamic: project-url
Dynamic: requires-dist
Dynamic: requires-python
Dynamic: summary
